pyfstat/__init__.py
pyfstat/_version.py
pyfstat/core.py
pyfstat/grid_based_searches.py
pyfstat/gridcorner.py
pyfstat/injection_parameters.py
pyfstat/logging.py
pyfstat/make_sfts.py
pyfstat/mcmc_based_searches.py
pyfstat/optimal_setup_functions.py
pyfstat/snr.py
pyfstat/tcw_fstat_map_funcs.py
pyfstat/pyCUDAkernels/cudaTransientFstatExpWindow.cu
pyfstat/pyCUDAkernels/cudaTransientFstatRectWindow.cu
pyfstat/utils/__init__.py
pyfstat/utils/atoms.py
pyfstat/utils/cli.py
pyfstat/utils/converting.py
pyfstat/utils/ephemeris.py
pyfstat/utils/formatting.py
pyfstat/utils/gsl.py
pyfstat/utils/importing.py
pyfstat/utils/io.py
pyfstat/utils/predict.py
pyfstat/utils/runlalsuite.py
pyfstat/utils/sft.py
pyfstat-2.3.0.dist-info/licenses/LICENSE
pyfstat-2.3.0.dist-info/METADATA
pyfstat-2.3.0.dist-info/WHEEL
pyfstat-2.3.0.dist-info/top_level.txt
pyfstat-2.3.0.dist-info/RECORD
