Metadata-Version: 2.4
Name: PyFstat
Version: 2.3.0
Summary: a python package for gravitational wave analysis with the F-statistic
Home-page: https://github.com/PyFstat/PyFstat
Author: Gregory Ashton, David Keitel, Reinhard Prix, Rodrigo Tenorio, Maria-Antonia Ferrer
Author-email: gregory.ashton@ligo.org
Maintainer: David Keitel
Maintainer-email: david.keitel@ligo.org
License: MIT
Project-URL: Changelog, https://github.com/PyFstat/PyFstat/blob/master/CHANGELOG.md
Project-URL: Documentation, https://pyfstat.readthedocs.io/
Project-URL: Issue tracker, https://github.com/PyFstat/PyFstat/issues
Platform: POSIX
Classifier: Programming Language :: Python :: 3
Classifier: License :: OSI Approved :: MIT License
Classifier: Operating System :: POSIX
Classifier: Natural Language :: English
Classifier: Intended Audience :: Science/Research
Classifier: Topic :: Scientific/Engineering :: Astronomy
Classifier: Topic :: Scientific/Engineering :: Physics
Requires-Python: >=3.9.0
License-File: LICENSE
Requires-Dist: attrs
Requires-Dist: corner
Requires-Dist: dill
Requires-Dist: matplotlib>=3.3
Requires-Dist: numpy
Requires-Dist: pandas
Requires-Dist: pathos
Requires-Dist: ptemcee
Requires-Dist: scipy
Requires-Dist: setuptools; python_version >= "3.12"
Requires-Dist: tqdm
Requires-Dist: lalsuite[lalpulsar]>=7.13
Provides-Extra: chainconsumer
Requires-Dist: chainconsumer<1.0; extra == "chainconsumer"
Provides-Extra: dev
Requires-Dist: pre-commit; extra == "dev"
Requires-Dist: sphinx==7.4.7; extra == "dev"
Requires-Dist: sphinx_autodoc_defaultargs==0.1.2; extra == "dev"
Requires-Dist: sphinx_autodoc_typehints==2.3.0; extra == "dev"
Requires-Dist: sphinx_gallery==0.17.1; extra == "dev"
Requires-Dist: sphinx_rtd_theme==2.0.0; extra == "dev"
Requires-Dist: m2r2==0.3.3.post2; extra == "dev"
Requires-Dist: mistune==0.8.4; extra == "dev"
Requires-Dist: pillow==10.4.0; extra == "dev"
Requires-Dist: black; extra == "dev"
Requires-Dist: codespell; extra == "dev"
Requires-Dist: flake8; extra == "dev"
Requires-Dist: flake8-docstrings; extra == "dev"
Requires-Dist: flake8-executable; extra == "dev"
Requires-Dist: flake8-isort; extra == "dev"
Requires-Dist: isort; extra == "dev"
Requires-Dist: pytest; extra == "dev"
Requires-Dist: pytest-cov; extra == "dev"
Requires-Dist: flaky; extra == "dev"
Requires-Dist: nbmake; extra == "dev"
Requires-Dist: wheel; extra == "dev"
Requires-Dist: check-wheel-contents; extra == "dev"
Provides-Extra: docs
Requires-Dist: sphinx==7.4.7; extra == "docs"
Requires-Dist: sphinx_autodoc_defaultargs==0.1.2; extra == "docs"
Requires-Dist: sphinx_autodoc_typehints==2.3.0; extra == "docs"
Requires-Dist: sphinx_gallery==0.17.1; extra == "docs"
Requires-Dist: sphinx_rtd_theme==2.0.0; extra == "docs"
Requires-Dist: m2r2==0.3.3.post2; extra == "docs"
Requires-Dist: mistune==0.8.4; extra == "docs"
Requires-Dist: pillow==10.4.0; extra == "docs"
Provides-Extra: pycuda
Requires-Dist: pycuda; extra == "pycuda"
Provides-Extra: style
Requires-Dist: black; extra == "style"
Requires-Dist: codespell; extra == "style"
Requires-Dist: flake8; extra == "style"
Requires-Dist: flake8-docstrings; extra == "style"
Requires-Dist: flake8-executable; extra == "style"
Requires-Dist: flake8-isort; extra == "style"
Requires-Dist: isort; extra == "style"
Provides-Extra: test
Requires-Dist: pytest; extra == "test"
Requires-Dist: pytest-cov; extra == "test"
Requires-Dist: flaky; extra == "test"
Requires-Dist: nbmake; extra == "test"
Provides-Extra: wheel
Requires-Dist: wheel; extra == "wheel"
Requires-Dist: check-wheel-contents; extra == "wheel"
Dynamic: author
Dynamic: author-email
Dynamic: classifier
Dynamic: description
Dynamic: description-content-type
Dynamic: home-page
Dynamic: license
Dynamic: license-file
Dynamic: maintainer
Dynamic: maintainer-email
Dynamic: platform
Dynamic: project-url
Dynamic: provides-extra
Dynamic: requires-dist
Dynamic: requires-python
Dynamic: summary
